sinhala
