Metadata-Version: 2.1
Name: Sinhala
Version: 1.1.0
Summary:  Sinhala Prastha Pirulu , Theravili, Thun theravili Sinhalen 
Home-page: https://github.com/dotLK/sinhala
Author: DotLK
Author-email: 
License: MIT
Keywords: Sinhala,Prastha Pirulu,Theravili,Thun theravili sinhalen
Classifier: Development Status :: 5 - Production/Stable
Classifier: Intended Audience :: Education
Classifier: Operating System :: Microsoft :: Windows :: Windows 10
Classifier: License :: OSI Approved :: MIT License
Classifier: Programming Language :: Python :: 3
License-File: LICENCE.txt
